ai_cmd/__init__.py
ai_cmd/cli.py
mia_terminal-0.1.0.dist-info/licenses/LICENSE
mia_terminal-0.1.0.dist-info/METADATA
mia_terminal-0.1.0.dist-info/WHEEL
mia_terminal-0.1.0.dist-info/entry_points.txt
mia_terminal-0.1.0.dist-info/top_level.txt
mia_terminal-0.1.0.dist-info/RECORD
