Metadata-Version: 2.4
Name: mia-terminal
Version: 0.1.0
Summary: A CLI tool that converts natural language to shell commands using OpenAI's API
Home-page: https://github.com/ronnybru/ai-cmd
Author: Ronny Bruknapp
Author-email: Ronny Bruknapp <ronny.bruknapp@digitaltrend.no>
License: MIT
Project-URL: Homepage, https://github.com/ronnybru/ai-cmd
Project-URL: Issues, https://github.com/ronnybru/ai-cmd/issues
Classifier: Programming Language :: Python :: 3
Classifier: License :: OSI Approved :: MIT License
Classifier: Operating System :: OS Independent
Requires-Python: >=3.6
License-File: LICENSE
Requires-Dist: openai>=1.0.0
Dynamic: author
Dynamic: home-page
Dynamic: license-file
Dynamic: requires-python
